README.md
setup.py
domain/__init__.py
domain/base.py
domain/client.py
domain/utils.py
domain/validate.py
domain.egg-info/PKG-INFO
domain.egg-info/SOURCES.txt
domain.egg-info/dependency_links.txt
domain.egg-info/requires.txt
domain.egg-info/top_level.txt
domain/authorisation/__init__.py
domain/authorisation/client_credentials.py
domain/authorisation/exceptions.py
domain/authorisation/grant.py
domain/authorisation/scopes.py
domain/authorisation/token.py