Metadata-Version: 2.1
Name: domain
Version: 0.1.4
Summary: Python client for the Domain property API
Home-page: UNKNOWN
Author: Andrew R. Casey
Author-email: andycasey@gmail.com
License: MIT
Keywords: domain property api client
Platform: UNKNOWN
Classifier: License :: OSI Approved :: MIT License
Classifier: Operating System :: OS Independent
Classifier: Programming Language :: Python :: 3.6
Provides-Extra: test
